appletlib/__init__.py
appletlib/app.py
appletlib/indicator.py
appletlib/posixsignal.py
appletlib/splash.py
appletlib/systray.py
appletlib-1.1.0.dist-info/LICENSE
appletlib-1.1.0.dist-info/METADATA
appletlib-1.1.0.dist-info/WHEEL
appletlib-1.1.0.dist-info/top_level.txt
appletlib-1.1.0.dist-info/RECORD
