Metadata-Version: 2.1
Name: appletlib
Version: 1.1.0
Summary: Python library providing a QSystemTrayIcon wrapper
Home-page: https://github.com/jmechnich/appletlib
Author: Joerg Mechnich
Author-email: joerg.mechnich@gmail.com
License: GNU GPLv3
Classifier: Programming Language :: Python :: 3
Classifier: License :: OSI Approved :: GNU General Public License v3 (GPLv3)
Classifier: Operating System :: POSIX :: Linux
Requires-Python: >=3.6
License-File: LICENSE
Requires-Dist: python-daemon
Requires-Dist: PyQt6
